django_frontify/__init__.py
django_frontify/fields.py
django_frontify/djangocms_frontify/__init__.py
django_frontify/djangocms_frontify/cms_plugins.py
django_frontify/djangocms_frontify/models.py
django_frontify/djangocms_frontify/migrations/0001_initial.py
django_frontify/djangocms_frontify/migrations/0002_auto_20231016_1026.py
django_frontify/djangocms_frontify/migrations/0003_frontifyimagepluginmodel_caption_text_db_and_more.py
django_frontify/djangocms_frontify/migrations/__init__.py
django_frontify/static/django_frontify/widget.css
django_frontify/static/django_frontify/widget.js
django_frontify/templates/admin/django_frontify/widgets/admin_file.html
django_frontify/templates/django_frontify/plugins/image.html
django_frontify/templatetags/__init__.py
django_frontify/templatetags/frontify_tags.py
django_frontify-0.8.0.dist-info/METADATA
django_frontify-0.8.0.dist-info/WHEEL
django_frontify-0.8.0.dist-info/top_level.txt
django_frontify-0.8.0.dist-info/RECORD
