Metadata-Version: 2.1
Name: django-frontify
Version: 0.8.0
Home-page: https://github.com/lab360-ch/django-frontify
Author: LAB360 GmbH
Author-email: info@lab360.ch
License: BSD
Classifier: Development Status :: 4 - Beta
Classifier: Environment :: Web Environment
Classifier: Intended Audience :: Developers
Classifier: License :: OSI Approved :: BSD License
Classifier: Operating System :: OS Independent
Classifier: Programming Language :: Python
Classifier: Programming Language :: Python :: 3
Classifier: Programming Language :: Python :: 3.7
Classifier: Framework :: Django
Classifier: Framework :: Django :: 2.2
Classifier: Framework :: Django CMS
Classifier: Framework :: Django CMS :: 3.7
